odoo/addons/product_category_multi_company/README.rst
odoo/addons/product_category_multi_company/__init__.py
odoo/addons/product_category_multi_company/__manifest__.py
odoo/addons/product_category_multi_company/i18n/product_category_multi_company.pot
odoo/addons/product_category_multi_company/models/__init__.py
odoo/addons/product_category_multi_company/models/product_category.py
odoo/addons/product_category_multi_company/models/product_template.py
odoo/addons/product_category_multi_company/readme/CONTRIBUTORS.rst
odoo/addons/product_category_multi_company/readme/DESCRIPTION.rst
odoo/addons/product_category_multi_company/readme/USAGE.rst
odoo/addons/product_category_multi_company/static/description/icon.png
odoo/addons/product_category_multi_company/static/description/index.html
odoo/addons/product_category_multi_company/tests/__init__.py
odoo/addons/product_category_multi_company/tests/test_product_category_multi_company.py
odoo/addons/product_category_multi_company/views/product_category.xml
odoo_addon_product_category_multi_company-15.0.1.0.0.2.dist-info/METADATA
odoo_addon_product_category_multi_company-15.0.1.0.0.2.dist-info/WHEEL
odoo_addon_product_category_multi_company-15.0.1.0.0.2.dist-info/top_level.txt
odoo_addon_product_category_multi_company-15.0.1.0.0.2.dist-info/RECORD
