Metadata-Version: 2.1
Name: odoo-addon-product_category_multi_company
Version: 15.0.1.0.0.2
Summary: Product Category multi-company
Home-page: https://github.com/OCA/multi-company
Author: ForgeFlow S.L.,Odoo Community Association (OCA)
Author-email: support@odoo-community.org
License: AGPL-3
Classifier: Programming Language :: Python
Classifier: Framework :: Odoo
Classifier: Framework :: Odoo :: 15.0
Classifier: License :: OSI Approved :: GNU Affero General Public License v3
Requires-Python: >=3.8
Requires-Dist: odoo-addon-base-multi-company<15.1dev,>=15.0dev
Requires-Dist: odoo-addon-product-category-inter-company<15.1dev,>=15.0dev
Requires-Dist: odoo-addon-product-multi-company<15.1dev,>=15.0dev
Requires-Dist: odoo<15.1dev,>=15.0a
